wfdserver/__init__.py
wfdserver/__main__.py
wfdserver/data/k6gte-wfdserver.desktop
wfdserver/data/k6gte.wfdserver-128.png
wfdserver/data/k6gte.wfdserver-32.png
wfdserver/data/k6gte.wfdserver-64.png
wfdserver/data/k6gte.wfdserver.svg
wfdserver/data/server_preferences.json
wfdserver/lib/__init__.py
wfdserver/lib/server_database.py
wfdserver/lib/version.py
wfdserver/lib/versiontest.py
wfdserver-24.2.19.dist-info/LICENSE.md
wfdserver-24.2.19.dist-info/METADATA
wfdserver-24.2.19.dist-info/WHEEL
wfdserver-24.2.19.dist-info/entry_points.txt
wfdserver-24.2.19.dist-info/top_level.txt
wfdserver-24.2.19.dist-info/RECORD
